LICENSE.txt
MANIFEST.in
README.txt
creds.txt
job_output.txt
setup.py
RedJack.egg-info/PKG-INFO
RedJack.egg-info/SOURCES.txt
RedJack.egg-info/dependency_links.txt
RedJack.egg-info/entry_points.txt
RedJack.egg-info/requires.txt
RedJack.egg-info/top_level.txt
redjack/__init__.py
redjack/agent.py
redjack/killableprocess.py
redjack/server.py
redjack/triggers.py
redjack/web.py
redjack/winprocess.py
redjack/js/build.js
redjack/js/build_line.js
redjack/js/build_lines.js
redjack/js/builds.js
redjack/js/cfg_settings.js
redjack/js/changes.js
redjack/js/common.js
redjack/js/jquery-1.4.2.min.js
redjack/js/machine.js
redjack/js/machines_group.js
redjack/js/machines_groups.js
redjack/js/script.js
redjack/js/trigger.js
redjack/js/triggers.js
redjack/media/HelvCondensed-Normal.otf
redjack/media/lcars-bg.png
redjack/templates/build.html
redjack/templates/build_line.html
redjack/templates/build_lines.html
redjack/templates/builds.html
redjack/templates/cfg_settings.html
redjack/templates/changes.html
redjack/templates/machine.html
redjack/templates/machines_group.html
redjack/templates/machines_groups.html
redjack/templates/main.html
redjack/templates/master.html
redjack/templates/master.html~
redjack/templates/script.html
redjack/templates/trigger.html
redjack/templates/triggers.html
redjack/templates/mail/master.html