Metadata-Version: 1.0
Name: RedJack
Version: 0.3.0
Summary: RedJack - continuous integration system.
Home-page: http://redjacklab.net/
Author: Michal Nowikowski
Author-email: godfryd@gmail.com
License: LICENSE.txt
Platform: UNKNOWN
